MANIFEST.in
README.md
setup.cfg
setup.py
version.txt
src/vdk/internal/heartbeat/config.py
src/vdk/internal/heartbeat/database_run_test.py
src/vdk/internal/heartbeat/empty_run_test.py
src/vdk/internal/heartbeat/hearbeat.py
src/vdk/internal/heartbeat/heartbeat_base_test.py
src/vdk/internal/heartbeat/heartbeat_test.py
src/vdk/internal/heartbeat/impala_database_test.py
src/vdk/internal/heartbeat/job_controller.py
src/vdk/internal/heartbeat/log_config.py
src/vdk/internal/heartbeat/main.py
src/vdk/internal/heartbeat/ping_frontend_test.py
src/vdk/internal/heartbeat/reporter.py
src/vdk/internal/heartbeat/simple_run_test.py
src/vdk/internal/heartbeat/successful_run_test.py
src/vdk/internal/heartbeat/tracing.py
src/vdk/internal/heartbeat/trino_database_test.py
src/vdk/internal/heartbeat/util.py
src/vdk/internal/heartbeat/vdk_heartbeat_data_job/database_ingestion/05_set_properties.py
src/vdk/internal/heartbeat/vdk_heartbeat_data_job/database_ingestion/10_ingest_data.py
src/vdk/internal/heartbeat/vdk_heartbeat_data_job/database_ingestion/20_verify_data.py
src/vdk/internal/heartbeat/vdk_heartbeat_data_job/database_ingestion/config.ini
src/vdk/internal/heartbeat/vdk_heartbeat_data_job/database_ingestion/requirements.txt
src/vdk/internal/heartbeat/vdk_heartbeat_data_job/empty/10_do_nothing.py
src/vdk/internal/heartbeat/vdk_heartbeat_data_job/empty/config.ini
src/vdk/internal/heartbeat/vdk_heartbeat_data_job/impala/05_set_properties.py
src/vdk/internal/heartbeat/vdk_heartbeat_data_job/impala/10_create_table_source.sql
src/vdk/internal/heartbeat/vdk_heartbeat_data_job/impala/15_create_table_destination.sql
src/vdk/internal/heartbeat/vdk_heartbeat_data_job/impala/16_create_table_load_destination.sql
src/vdk/internal/heartbeat/vdk_heartbeat_data_job/impala/20_move_data_using_load.py
src/vdk/internal/heartbeat/vdk_heartbeat_data_job/impala/30_move_data_using_sql.sql
src/vdk/internal/heartbeat/vdk_heartbeat_data_job/impala/40_execute_template.py
src/vdk_heartbeat.egg-info/PKG-INFO
src/vdk_heartbeat.egg-info/SOURCES.txt
src/vdk_heartbeat.egg-info/dependency_links.txt
src/vdk_heartbeat.egg-info/entry_points.txt
src/vdk_heartbeat.egg-info/not-zip-safe
src/vdk_heartbeat.egg-info/requires.txt
src/vdk_heartbeat.egg-info/top_level.txt