Metadata-Version: 2.1
Name: vdk-heartbeat
Version: 0.6.874308419
Summary: Versatile Data Kit Heartbeat and Health Test
Home-page: https://github.com/vmware/versatile-data-kit/tree/main/projects/vdk-heartbeat
Author: VMware Inc.
Author-email: taurus@groups.vmware.com
Project-URL: Documentation, https://github.com/vmware/versatile-data-kit/wiki/Introduction
Project-URL: Source, https://github.com/vmware/versatile-data-kit/tree/main/projects/vdk-heartbeat
Platform: any
Classifier: Development Status :: 4 - Beta
Classifier: License :: OSI Approved :: Apache Software License
Classifier: Programming Language :: Python
Classifier: Programming Language :: Python :: 3.7
Classifier: Programming Language :: Python :: 3.8
Classifier: Programming Language :: Python :: 3.9
Classifier: Programming Language :: Python :: 3.10
Classifier: Programming Language :: Python :: 3.11
Requires-Python: <4,>=3.7
Provides-Extra: trino
Provides-Extra: impala
Provides-Extra: taurus
